apistar_cors.py
apistar_cors-0.2.1.dist-info/DESCRIPTION.rst
apistar_cors-0.2.1.dist-info/METADATA
apistar_cors-0.2.1.dist-info/RECORD
apistar_cors-0.2.1.dist-info/WHEEL
apistar_cors-0.2.1.dist-info/metadata.json
apistar_cors-0.2.1.dist-info/top_level.txt
