Metadata-Version: 2.0
Name: apistar-cors
Version: 0.2.1
Summary: CORS support for API Star.
Home-page: UNKNOWN
License: UNKNOWN
Platform: UNKNOWN
Requires-Python: >=3.5
Requires-Dist: apistar (>=0.4)
Requires-Dist: wsgicors (<0.8,>=0.7)
